[
  {
    "id": "q_3_0600",
    "page": [
      143
    ],
    "entry": {
      "id": "q_3_0600",
      "question": "연수휴직은 어디서 연수받을 때 가능한가요?",
      "answer": "연수휴직은 **국내**에 있는 교육기관에서 **학위취득**을 목적으로 할 때 가능합니다.\n\n경기도교육청 규칙에 따른 **연수기관:**\n1. 「고등교육법」 제2조의 대학·산업대학·교육대학 중 대학원이 설치된 대학\n2. 「고등교육법」 제30조에 따른 대학원대학\n3. 한국학중앙연구원\n4. 한국과학기술원\n\n**연수휴직 불가 사유:**\n- 원격대학원은 제외\n- 야간수업, 계절수업 및 시간수업은 제외\n- 대학원에서 교육과정을 수료한 후 학위논문 작성만을 위한 휴직은 불가\n- 연구소나 대학원에서 연구원으로 활동하기 위한 사유는 불가\n\n※ 지도교과 또는 전공교과와 관련된 석사 또는 박사 학위 취득 목적에 한함",
      "sources": [
        {
          "page": 143,
          "title": "연수기관 지정",
          "text": "교육공무원이 연수휴직을 하고 연수를 받을 수 있는 연수기관은 다음 각 호와 같다. 다만, 원격대학원은 제외한다. 1. 「고등교육법」제2조의 대학·산업대학·교육대학 중 대학원이 설치된 대학 2. 「고등교육법」제30조에 따른 대학원대학 3. 한국학중앙연구원 4. 한국과학기술원"
        },
        {
          "page": 143,
          "title": "연수휴직의 범위",
          "text": "지도교과 또는 전공교과와 관련된 석사 또는 박사 학위 취득 목적에 한하여 연수휴직을 허가할 수 있다. 다만, 야간수업, 계절수업 및 시간수업은 제외한다."
        }
      ],
      "category": "휴직 및 복직",
      "subcategory": "연수휴직",
      "keywords": [
        "연수휴직",
        "연수기관",
        "대학원",
        "학위취득",
        "석사박사"
      ]
    }
  },
  {
    "id": "q_3_0608",
    "page": [
      143
    ],
    "entry": {
      "id": "q_3_0608",
      "question": "경기도교육청 교육공무원 연수휴직을 위한 연수기관 지정에 관한 규칙은 무엇인가요?",
      "answer": "경기도교육청 교육공무원 연수휴직을 위한 연수기관 지정에 관한 규칙을 안내드립니다.\n\n**핵심 내용:**\n경기도 교육규칙 제583호 2009.08.07.\n\n**제1조(목적):** 이 규칙은 「교육공무원법」제44조 제1항 제8호, 「행정 권한의 위임 및 위탁에 관한 규정」제26조 제1항 제32호 및 「교육공무원인사관리규정」제24조에 따라 경기도교육청 소속 교육공무원의 연수휴직을 위한 연수기관 지정과 연수휴직의 범위 등을 규정함을 목적으로 한다.\n**제2조(정의):** 이 규칙에서 사용하는 용어의 뜻은 다음과 같다.\n1. \"연수휴직\"이란 「교육공무원법」제44조 제1항 제8호에 따라 임용권자로부터 허가를 받아 휴직함을 말한다.\n2. \"연수기관\"이란 연수휴직을 하고 연수를 받을 수 있는 국내의 연구기관이나 교육기관 등을 말한다.\n**제3조(적용 범위):** 이 규칙은 「초·중등교육법」제2조에 규정된 공립의 각급 학교에서 근무하는 교원과 교육기관·교육행정기관 및 교육연구기관에서 근무하는 교육전문직공무원에게 적용한다.\n**제4조(연수기관의 지정):** 「행정 권한의 위임 및 위탁에 관한 규정」제26조 제1항 제32호에 따라 교육공무원이 연수휴직을 하고 연수를 받을 수 있는 연수기관은 다음 각 호와 같다. 다만, 원격대학원은 제외한다.\n1. 「고등교육법」제2조의 대학·산업대학·교육대학 중 대학원이 설치된 대학\n2. 「고등교육법」제30조에 따른 대학원대학\n3. 한국학중앙연구원\n**제5조(연수휴직의 범위):** 임용권자는 제4조에 따른 연수기관에서 지도교과 또는 전공교과와 관련된 석사 또는 박사 학위 취득 목적에 한하여 연수휴직을 허가할 수 있다. 다만, 야간수업, 계절수업 및 시간수업은 제외한다.\n\n**관련 근거:** 「교육공무원법」 제44조, 「행정 권한의 위임 및 위탁에 관한 규정」 제26조, 「교육공무원인사관리규정」 제24조, 「초·중등교육법」 제2조",
      "sources": [
        {
          "page": 143,
          "title": "경기도교육청 교육공무원 연수휴직을 위한 연수기관 지정에 관한 규칙",
          "text": "경기도 교육규칙 제583호 2009.08.07.\n**제1조(목적)** 이 규칙은 「교육공무원법」제44조 제1항 제8호, 「행정 권한의 위임 및 위탁에 관한 규정」제26조 제1항 제32호 및 「교육공무원인사관리규정」제24조에 따라 경기도교육청 소속 교육공무원의 연수휴직을 위한 연수기관 지정과 연수휴직의 범위 등을 규정함을 목적으로 한다.\n**제2조(정의)** 이 규칙에서 사용하는 용어의 뜻은 다음과 같다.\n1. \"연수휴직\"이란 「교육공무원법」제44조 제1항 제8호에 따라 임용권자로부터 허가를 받아 휴직함을 말한다.\n2. \"연수기관\"이란 연수휴직을 하고 연수를 받을 수 있는 국내의 연구기관이나 교육기관 등을 말한다.\n**제3조(적용 범위)** 이 규칙은 「초·중등교육법」제2조에 규정된 공립의 각급 학교에서 근무하는 교원과 교육기관·교육행정기관 및 교육연구기관에서 근무하는 교육전문직공무원에게 적용한다."
        }
      ],
      "category": "휴직 및 복직",
      "subcategory": "휴직 및 복직",
      "keywords": [
        "임용",
        "제1조(목적)",
        "제3조(적용 범위)",
        "제4조(연수기관의 지정)",
        "휴직"
      ]
    }
  },
  {
    "id": "q_3_0609",
    "page": [
      143
    ],
    "entry": {
      "id": "q_3_0609",
      "question": "경기도교육청 교육공무원 연수휴직을 위한 연수기관 지정에 관한 규칙의 정의가 어떻게 되나요?",
      "answer": "경기도교육청 교육공무원 연수휴직을 위한 연수기관 지정에 관한 규칙에 대해 안내드립니다.\n\n**핵심 내용:**\n경기도 교육규칙 제583호 2009.08.07.\n\n**제1조(목적):** 이 규칙은 「교육공무원법」제44조 제1항 제8호, 「행정 권한의 위임 및 위탁에 관한 규정」제26조 제1항 제32호 및 「교육공무원인사관리규정」제24조에 따라 경기도교육청 소속 교육공무원의 연수휴직을 위한 연수기관 지정과 연수휴직의 범위 등을 규정함을 목적으로 한다.\n**제2조(정의):** 이 규칙에서 사용하는 용어의 뜻은 다음과 같다.\n1. \"연수휴직\"이란 「교육공무원법」제44조 제1항 제8호에 따라 임용권자로부터 허가를 받아 휴직함을 말한다.\n2. \"연수기관\"이란 연수휴직을 하고 연수를 받을 수 있는 국내의 연구기관이나 교육기관 등을 말한다.\n**제3조(적용 범위):** 이 규칙은 「초·중등교육법」제2조에 규정된 공립의 각급 학교에서 근무하는 교원과 교육기관·교육행정기관 및 교육연구기관에서 근무하는 교육전문직공무원에게 적용한다.\n**제4조(연수기관의 지정):** 「행정 권한의 위임 및 위탁에 관한 규정」제26조 제1항 제32호에 따라 교육공무원이 연수휴직을 하고 연수를 받을 수 있는 연수기관은 다음 각 호와 같다. 다만, 원격대학원은 제외한다.\n1. 「고등교육법」제2조의 대학·산업대학·교육대학 중 대학원이 설치된 대학\n2. 「고등교육법」제30조에 따른 대학원대학\n3. 한국학중앙연구원\n**제5조(연수휴직의 범위):** 임용권자는 제4조에 따른 연수기관에서 지도교과 또는 전공교과와 관련된 석사 또는 박사 학위 취득 목적에 한하여 연수휴직을 허가할 수 있다. 다만, 야간수업, 계절수업 및 시간수업은 제외한다.\n\n**관련 근거:** 「교육공무원법」 제44조, 「행정 권한의 위임 및 위탁에 관한 규정」 제26조, 「교육공무원인사관리규정」 제24조, 「초·중등교육법」 제2조",
      "sources": [
        {
          "page": 143,
          "title": "경기도교육청 교육공무원 연수휴직을 위한 연수기관 지정에 관한 규칙",
          "text": "경기도 교육규칙 제583호 2009.08.07.\n**제1조(목적)** 이 규칙은 「교육공무원법」제44조 제1항 제8호, 「행정 권한의 위임 및 위탁에 관한 규정」제26조 제1항 제32호 및 「교육공무원인사관리규정」제24조에 따라 경기도교육청 소속 교육공무원의 연수휴직을 위한 연수기관 지정과 연수휴직의 범위 등을 규정함을 목적으로 한다.\n**제2조(정의)** 이 규칙에서 사용하는 용어의 뜻은 다음과 같다.\n1. \"연수휴직\"이란 「교육공무원법」제44조 제1항 제8호에 따라 임용권자로부터 허가를 받아 휴직함을 말한다.\n2. \"연수기관\"이란 연수휴직을 하고 연수를 받을 수 있는 국내의 연구기관이나 교육기관 등을 말한다.\n**제3조(적용 범위)** 이 규칙은 「초·중등교육법」제2조에 규정된 공립의 각급 학교에서 근무하는 교원과 교육기관·교육행정기관 및 교육연구기관에서 근무하는 교육전문직공무원에게 적용한다."
        }
      ],
      "category": "휴직 및 복직",
      "subcategory": "휴직 및 복직",
      "keywords": [
        "임용",
        "제1조(목적)",
        "제3조(적용 범위)",
        "제4조(연수기관의 지정)",
        "휴직"
      ]
    }
  },
  {
    "id": "q_3_0611",
    "page": [
      143
    ],
    "entry": {
      "id": "q_3_0611",
      "question": "경기도교육청 교육공무원 연수휴직을 위한 연수기관 지정에 관한 규칙하면 어떤 효과가 있나요?",
      "answer": "경기도교육청 교육공무원 연수휴직을 위한 연수기관 지정에 관한 규칙에 대해 설명드리겠습니다.\n\n**핵심 내용:**\n경기도 교육규칙 제583호 2009.08.07.\n\n**제1조(목적):** 이 규칙은 「교육공무원법」제44조 제1항 제8호, 「행정 권한의 위임 및 위탁에 관한 규정」제26조 제1항 제32호 및 「교육공무원인사관리규정」제24조에 따라 경기도교육청 소속 교육공무원의 연수휴직을 위한 연수기관 지정과 연수휴직의 범위 등을 규정함을 목적으로 한다.\n**제2조(정의):** 이 규칙에서 사용하는 용어의 뜻은 다음과 같다.\n1. \"연수휴직\"이란 「교육공무원법」제44조 제1항 제8호에 따라 임용권자로부터 허가를 받아 휴직함을 말한다.\n2. \"연수기관\"이란 연수휴직을 하고 연수를 받을 수 있는 국내의 연구기관이나 교육기관 등을 말한다.\n**제3조(적용 범위):** 이 규칙은 「초·중등교육법」제2조에 규정된 공립의 각급 학교에서 근무하는 교원과 교육기관·교육행정기관 및 교육연구기관에서 근무하는 교육전문직공무원에게 적용한다.\n**제4조(연수기관의 지정):** 「행정 권한의 위임 및 위탁에 관한 규정」제26조 제1항 제32호에 따라 교육공무원이 연수휴직을 하고 연수를 받을 수 있는 연수기관은 다음 각 호와 같다. 다만, 원격대학원은 제외한다.\n1. 「고등교육법」제2조의 대학·산업대학·교육대학 중 대학원이 설치된 대학\n2. 「고등교육법」제30조에 따른 대학원대학\n3. 한국학중앙연구원\n**제5조(연수휴직의 범위):** 임용권자는 제4조에 따른 연수기관에서 지도교과 또는 전공교과와 관련된 석사 또는 박사 학위 취득 목적에 한하여 연수휴직을 허가할 수 있다. 다만, 야간수업, 계절수업 및 시간수업은 제외한다.\n\n**관련 근거:** 「교육공무원법」 제44조, 「행정 권한의 위임 및 위탁에 관한 규정」 제26조, 「교육공무원인사관리규정」 제24조, 「초·중등교육법」 제2조",
      "sources": [
        {
          "page": 143,
          "title": "경기도교육청 교육공무원 연수휴직을 위한 연수기관 지정에 관한 규칙",
          "text": "경기도 교육규칙 제583호 2009.08.07.\n**제1조(목적)** 이 규칙은 「교육공무원법」제44조 제1항 제8호, 「행정 권한의 위임 및 위탁에 관한 규정」제26조 제1항 제32호 및 「교육공무원인사관리규정」제24조에 따라 경기도교육청 소속 교육공무원의 연수휴직을 위한 연수기관 지정과 연수휴직의 범위 등을 규정함을 목적으로 한다.\n**제2조(정의)** 이 규칙에서 사용하는 용어의 뜻은 다음과 같다.\n1. \"연수휴직\"이란 「교육공무원법」제44조 제1항 제8호에 따라 임용권자로부터 허가를 받아 휴직함을 말한다.\n2. \"연수기관\"이란 연수휴직을 하고 연수를 받을 수 있는 국내의 연구기관이나 교육기관 등을 말한다.\n**제3조(적용 범위)** 이 규칙은 「초·중등교육법」제2조에 규정된 공립의 각급 학교에서 근무하는 교원과 교육기관·교육행정기관 및 교육연구기관에서 근무하는 교육전문직공무원에게 적용한다."
        }
      ],
      "category": "휴직 및 복직",
      "subcategory": "휴직 및 복직",
      "keywords": [
        "임용",
        "제1조(목적)",
        "제3조(적용 범위)",
        "제4조(연수기관의 지정)",
        "휴직"
      ]
    }
  },
  {
    "id": "q_3_0612",
    "page": [
      143
    ],
    "entry": {
      "id": "q_3_0612",
      "question": "경기도교육청 교육공무원 연수휴직을 위한 연수기관 지정에 관한 규칙 대상자는 어떻게 선발하나요?",
      "answer": "경기도교육청 교육공무원 연수휴직을 위한 연수기관 지정에 관한 규칙에 관해 안내드립니다.\n\n**핵심 내용:**\n경기도 교육규칙 제583호 2009.08.07.\n\n**제1조(목적):** 이 규칙은 「교육공무원법」제44조 제1항 제8호, 「행정 권한의 위임 및 위탁에 관한 규정」제26조 제1항 제32호 및 「교육공무원인사관리규정」제24조에 따라 경기도교육청 소속 교육공무원의 연수휴직을 위한 연수기관 지정과 연수휴직의 범위 등을 규정함을 목적으로 한다.\n**제2조(정의):** 이 규칙에서 사용하는 용어의 뜻은 다음과 같다.\n1. \"연수휴직\"이란 「교육공무원법」제44조 제1항 제8호에 따라 임용권자로부터 허가를 받아 휴직함을 말한다.\n2. \"연수기관\"이란 연수휴직을 하고 연수를 받을 수 있는 국내의 연구기관이나 교육기관 등을 말한다.\n**제3조(적용 범위):** 이 규칙은 「초·중등교육법」제2조에 규정된 공립의 각급 학교에서 근무하는 교원과 교육기관·교육행정기관 및 교육연구기관에서 근무하는 교육전문직공무원에게 적용한다.\n**제4조(연수기관의 지정):** 「행정 권한의 위임 및 위탁에 관한 규정」제26조 제1항 제32호에 따라 교육공무원이 연수휴직을 하고 연수를 받을 수 있는 연수기관은 다음 각 호와 같다. 다만, 원격대학원은 제외한다.\n1. 「고등교육법」제2조의 대학·산업대학·교육대학 중 대학원이 설치된 대학\n2. 「고등교육법」제30조에 따른 대학원대학\n3. 한국학중앙연구원\n**제5조(연수휴직의 범위):** 임용권자는 제4조에 따른 연수기관에서 지도교과 또는 전공교과와 관련된 석사 또는 박사 학위 취득 목적에 한하여 연수휴직을 허가할 수 있다. 다만, 야간수업, 계절수업 및 시간수업은 제외한다.\n\n**관련 근거:** 「교육공무원법」 제44조, 「행정 권한의 위임 및 위탁에 관한 규정」 제26조, 「교육공무원인사관리규정」 제24조, 「초·중등교육법」 제2조",
      "sources": [
        {
          "page": 143,
          "title": "경기도교육청 교육공무원 연수휴직을 위한 연수기관 지정에 관한 규칙",
          "text": "경기도 교육규칙 제583호 2009.08.07.\n**제1조(목적)** 이 규칙은 「교육공무원법」제44조 제1항 제8호, 「행정 권한의 위임 및 위탁에 관한 규정」제26조 제1항 제32호 및 「교육공무원인사관리규정」제24조에 따라 경기도교육청 소속 교육공무원의 연수휴직을 위한 연수기관 지정과 연수휴직의 범위 등을 규정함을 목적으로 한다.\n**제2조(정의)** 이 규칙에서 사용하는 용어의 뜻은 다음과 같다.\n1. \"연수휴직\"이란 「교육공무원법」제44조 제1항 제8호에 따라 임용권자로부터 허가를 받아 휴직함을 말한다.\n2. \"연수기관\"이란 연수휴직을 하고 연수를 받을 수 있는 국내의 연구기관이나 교육기관 등을 말한다.\n**제3조(적용 범위)** 이 규칙은 「초·중등교육법」제2조에 규정된 공립의 각급 학교에서 근무하는 교원과 교육기관·교육행정기관 및 교육연구기관에서 근무하는 교육전문직공무원에게 적용한다."
        }
      ],
      "category": "휴직 및 복직",
      "subcategory": "휴직 및 복직",
      "keywords": [
        "임용",
        "제1조(목적)",
        "제3조(적용 범위)",
        "제4조(연수기관의 지정)",
        "휴직"
      ]
    }
  },
  {
    "id": "q_3_0613",
    "page": [
      143
    ],
    "entry": {
      "id": "q_3_0613",
      "question": "경기도교육청 교육공무원 연수휴직을 위한 연수기관 지정에 관한 규칙의 원칙은 무엇인가요?",
      "answer": "경기도교육청 교육공무원 연수휴직을 위한 연수기관 지정에 관한 규칙 관련 사항을 설명드리겠습니다.\n\n**핵심 내용:**\n경기도 교육규칙 제583호 2009.08.07.\n\n**제1조(목적):** 이 규칙은 「교육공무원법」제44조 제1항 제8호, 「행정 권한의 위임 및 위탁에 관한 규정」제26조 제1항 제32호 및 「교육공무원인사관리규정」제24조에 따라 경기도교육청 소속 교육공무원의 연수휴직을 위한 연수기관 지정과 연수휴직의 범위 등을 규정함을 목적으로 한다.\n**제2조(정의):** 이 규칙에서 사용하는 용어의 뜻은 다음과 같다.\n1. \"연수휴직\"이란 「교육공무원법」제44조 제1항 제8호에 따라 임용권자로부터 허가를 받아 휴직함을 말한다.\n2. \"연수기관\"이란 연수휴직을 하고 연수를 받을 수 있는 국내의 연구기관이나 교육기관 등을 말한다.\n**제3조(적용 범위):** 이 규칙은 「초·중등교육법」제2조에 규정된 공립의 각급 학교에서 근무하는 교원과 교육기관·교육행정기관 및 교육연구기관에서 근무하는 교육전문직공무원에게 적용한다.\n**제4조(연수기관의 지정):** 「행정 권한의 위임 및 위탁에 관한 규정」제26조 제1항 제32호에 따라 교육공무원이 연수휴직을 하고 연수를 받을 수 있는 연수기관은 다음 각 호와 같다. 다만, 원격대학원은 제외한다.\n1. 「고등교육법」제2조의 대학·산업대학·교육대학 중 대학원이 설치된 대학\n2. 「고등교육법」제30조에 따른 대학원대학\n3. 한국학중앙연구원\n**제5조(연수휴직의 범위):** 임용권자는 제4조에 따른 연수기관에서 지도교과 또는 전공교과와 관련된 석사 또는 박사 학위 취득 목적에 한하여 연수휴직을 허가할 수 있다. 다만, 야간수업, 계절수업 및 시간수업은 제외한다.\n\n**관련 근거:** 「교육공무원법」 제44조, 「행정 권한의 위임 및 위탁에 관한 규정」 제26조, 「교육공무원인사관리규정」 제24조, 「초·중등교육법」 제2조",
      "sources": [
        {
          "page": 143,
          "title": "경기도교육청 교육공무원 연수휴직을 위한 연수기관 지정에 관한 규칙",
          "text": "경기도 교육규칙 제583호 2009.08.07.\n**제1조(목적)** 이 규칙은 「교육공무원법」제44조 제1항 제8호, 「행정 권한의 위임 및 위탁에 관한 규정」제26조 제1항 제32호 및 「교육공무원인사관리규정」제24조에 따라 경기도교육청 소속 교육공무원의 연수휴직을 위한 연수기관 지정과 연수휴직의 범위 등을 규정함을 목적으로 한다.\n**제2조(정의)** 이 규칙에서 사용하는 용어의 뜻은 다음과 같다.\n1. \"연수휴직\"이란 「교육공무원법」제44조 제1항 제8호에 따라 임용권자로부터 허가를 받아 휴직함을 말한다.\n2. \"연수기관\"이란 연수휴직을 하고 연수를 받을 수 있는 국내의 연구기관이나 교육기관 등을 말한다.\n**제3조(적용 범위)** 이 규칙은 「초·중등교육법」제2조에 규정된 공립의 각급 학교에서 근무하는 교원과 교육기관·교육행정기관 및 교육연구기관에서 근무하는 교육전문직공무원에게 적용한다."
        }
      ],
      "category": "휴직 및 복직",
      "subcategory": "휴직 및 복직",
      "keywords": [
        "임용",
        "제1조(목적)",
        "제3조(적용 범위)",
        "제4조(연수기관의 지정)",
        "휴직"
      ]
    }
  },
  {
    "id": "q_3_0614",
    "page": [
      143
    ],
    "entry": {
      "id": "q_3_0614",
      "question": "경기도교육청 교육공무원 연수휴직을 위한 연수기관 지정에 관한 규칙 관련하여 자주 묻는 질문이 있나요?",
      "answer": "경기도교육청 교육공무원 연수휴직을 위한 연수기관 지정에 관한 규칙의 내용을 설명드리겠습니다.\n\n**핵심 내용:**\n경기도 교육규칙 제583호 2009.08.07.\n\n**제1조(목적):** 이 규칙은 「교육공무원법」제44조 제1항 제8호, 「행정 권한의 위임 및 위탁에 관한 규정」제26조 제1항 제32호 및 「교육공무원인사관리규정」제24조에 따라 경기도교육청 소속 교육공무원의 연수휴직을 위한 연수기관 지정과 연수휴직의 범위 등을 규정함을 목적으로 한다.\n**제2조(정의):** 이 규칙에서 사용하는 용어의 뜻은 다음과 같다.\n1. \"연수휴직\"이란 「교육공무원법」제44조 제1항 제8호에 따라 임용권자로부터 허가를 받아 휴직함을 말한다.\n2. \"연수기관\"이란 연수휴직을 하고 연수를 받을 수 있는 국내의 연구기관이나 교육기관 등을 말한다.\n**제3조(적용 범위):** 이 규칙은 「초·중등교육법」제2조에 규정된 공립의 각급 학교에서 근무하는 교원과 교육기관·교육행정기관 및 교육연구기관에서 근무하는 교육전문직공무원에게 적용한다.\n**제4조(연수기관의 지정):** 「행정 권한의 위임 및 위탁에 관한 규정」제26조 제1항 제32호에 따라 교육공무원이 연수휴직을 하고 연수를 받을 수 있는 연수기관은 다음 각 호와 같다. 다만, 원격대학원은 제외한다.\n1. 「고등교육법」제2조의 대학·산업대학·교육대학 중 대학원이 설치된 대학\n2. 「고등교육법」제30조에 따른 대학원대학\n3. 한국학중앙연구원\n**제5조(연수휴직의 범위):** 임용권자는 제4조에 따른 연수기관에서 지도교과 또는 전공교과와 관련된 석사 또는 박사 학위 취득 목적에 한하여 연수휴직을 허가할 수 있다. 다만, 야간수업, 계절수업 및 시간수업은 제외한다.\n\n**관련 근거:** 「교육공무원법」 제44조, 「행정 권한의 위임 및 위탁에 관한 규정」 제26조, 「교육공무원인사관리규정」 제24조, 「초·중등교육법」 제2조",
      "sources": [
        {
          "page": 143,
          "title": "경기도교육청 교육공무원 연수휴직을 위한 연수기관 지정에 관한 규칙",
          "text": "경기도 교육규칙 제583호 2009.08.07.\n**제1조(목적)** 이 규칙은 「교육공무원법」제44조 제1항 제8호, 「행정 권한의 위임 및 위탁에 관한 규정」제26조 제1항 제32호 및 「교육공무원인사관리규정」제24조에 따라 경기도교육청 소속 교육공무원의 연수휴직을 위한 연수기관 지정과 연수휴직의 범위 등을 규정함을 목적으로 한다.\n**제2조(정의)** 이 규칙에서 사용하는 용어의 뜻은 다음과 같다.\n1. \"연수휴직\"이란 「교육공무원법」제44조 제1항 제8호에 따라 임용권자로부터 허가를 받아 휴직함을 말한다.\n2. \"연수기관\"이란 연수휴직을 하고 연수를 받을 수 있는 국내의 연구기관이나 교육기관 등을 말한다.\n**제3조(적용 범위)** 이 규칙은 「초·중등교육법」제2조에 규정된 공립의 각급 학교에서 근무하는 교원과 교육기관·교육행정기관 및 교육연구기관에서 근무하는 교육전문직공무원에게 적용한다."
        }
      ],
      "category": "휴직 및 복직",
      "subcategory": "휴직 및 복직",
      "keywords": [
        "임용",
        "제1조(목적)",
        "제3조(적용 범위)",
        "제4조(연수기관의 지정)",
        "휴직"
      ]
    }
  },
  {
    "id": "q_3_0619",
    "page": [
      143
    ],
    "entry": {
      "id": "q_3_0619",
      "question": "경기도교육청 교육공무원 연수휴직을 위한 연수기관 지정에 관한 규칙의 세부 기준을 설명해주세요.",
      "answer": "경기도교육청 교육공무원 연수휴직을 위한 연수기관 지정에 관한 규칙의 주요 내용을 정리해 드리겠습니다.\n\n**주요 내용:**\n- 경기도 교육규칙 제583호 2009.08.07.\n- **제1조(목적):** 이 규칙은 「교육공무원법」제44조 제1항 제8호, 「행정 권한의 위임 및 위탁에 관한 규정」제26조 제1항 제32호 및 「교육공무원인사관리규정」제24조에 따라 경기도교육청 소속 교육공무원의 연수휴직을 위한 연수기관 지정과 연수휴직의 범위 등을 규정함을 목적으로 한다.\n- **제2조(정의):** 이 규칙에서 사용하는 용어의 뜻은 다음과 같다.\n\n**세부 사항:**\n- 1. \"연수휴직\"이란 「교육공무원법」제44조 제1항 제8호에 따라 임용권자로부터 허가를 받아 휴직함을 말한다.\n- 2. \"연수기관\"이란 연수휴직을 하고 연수를 받을 수 있는 국내의 연구기관이나 교육기관 등을 말한다.\n- **제3조(적용 범위):** 이 규칙은 「초·중등교육법」제2조에 규정된 공립의 각급 학교에서 근무하는 교원과 교육기관·교육행정기관 및 교육연구기관에서 근무하는 교육전문직공무원에게 적용한다.\n- **제4조(연수기관의 지정):** 「행정 권한의 위임 및 위탁에 관한 규정」제26조 제1항 제32호에 따라 교육공무원이 연수휴직을 하고 연수를 받을 수 있는 연수기관은 다음 각 호와 같다. 다만, 원격대학원은 제외한다.\n- 1. 「고등교육법」제2조의 대학·산업대학·교육대학 중 대학원이 설치된 대학\n\n**관련 법령:** 「교육공무원법」 제44조, 「행정 권한의 위임 및 위탁에 관한 규정」 제26조, 「교육공무원인사관리규정」 제24조, 「초·중등교육법」 제2조",
      "sources": [
        {
          "page": 143,
          "title": "경기도교육청 교육공무원 연수휴직을 위한 연수기관 지정에 관한 규칙",
          "text": "경기도 교육규칙 제583호 2009.08.07.\n**제1조(목적)** 이 규칙은 「교육공무원법」제44조 제1항 제8호, 「행정 권한의 위임 및 위탁에 관한 규정」제26조 제1항 제32호 및 「교육공무원인사관리규정」제24조에 따라 경기도교육청 소속 교육공무원의 연수휴직을 위한 연수기관 지정과 연수휴직의 범위 등을 규정함을 목적으로 한다.\n**제2조(정의)** 이 규칙에서 사용하는 용어의 뜻은 다음과 같다.\n1. \"연수휴직\"이란 「교육공무원법」제44조 제1항 제8호에 따라 임용권자로부터 허가를 받아 휴직함을 말한다.\n2. \"연수기관\"이란 연수휴직을 하고 연수를 받을 수 있는 국내의 연구기관이나 교육기관 등을 말한다.\n**제3조(적용 범위)** 이 규칙은 「초·중등교육법」제2조에 규정된 공립의 각급 학교에서 근무하는 교원과 교육기관·교육행정기관 및 교육연구기관에서 근무하는 교육전문직공무원에게 적용한다."
        }
      ],
      "category": "휴직 및 복직",
      "subcategory": "휴직 및 복직",
      "keywords": [
        "제2조(정의)",
        "휴직",
        "행정 권한의 위임 및 위탁에 관한 규정",
        "제1조(목적)",
        "교육공무원법",
        "교육공무원인사관리규정"
      ]
    }
  },
  {
    "id": "q_3_0620",
    "page": [
      143
    ],
    "entry": {
      "id": "q_3_0620",
      "question": "경기도교육청 교육공무원 연수휴직을 위한 연수기관 지정에 관한 규칙에서 가장 중요한 조건은 무엇인가요?",
      "answer": "질문하신 경기도교육청 교육공무원 연수휴직을 위한 연수기관 지정에 관한 규칙에 대해 답변드립니다.\n\n**주요 내용:**\n- 경기도 교육규칙 제583호 2009.08.07.\n- **제1조(목적):** 이 규칙은 「교육공무원법」제44조 제1항 제8호, 「행정 권한의 위임 및 위탁에 관한 규정」제26조 제1항 제32호 및 「교육공무원인사관리규정」제24조에 따라 경기도교육청 소속 교육공무원의 연수휴직을 위한 연수기관 지정과 연수휴직의 범위 등을 규정함을 목적으로 한다.\n- **제2조(정의):** 이 규칙에서 사용하는 용어의 뜻은 다음과 같다.\n\n**세부 사항:**\n- 1. \"연수휴직\"이란 「교육공무원법」제44조 제1항 제8호에 따라 임용권자로부터 허가를 받아 휴직함을 말한다.\n- 2. \"연수기관\"이란 연수휴직을 하고 연수를 받을 수 있는 국내의 연구기관이나 교육기관 등을 말한다.\n- **제3조(적용 범위):** 이 규칙은 「초·중등교육법」제2조에 규정된 공립의 각급 학교에서 근무하는 교원과 교육기관·교육행정기관 및 교육연구기관에서 근무하는 교육전문직공무원에게 적용한다.\n- **제4조(연수기관의 지정):** 「행정 권한의 위임 및 위탁에 관한 규정」제26조 제1항 제32호에 따라 교육공무원이 연수휴직을 하고 연수를 받을 수 있는 연수기관은 다음 각 호와 같다. 다만, 원격대학원은 제외한다.\n- 1. 「고등교육법」제2조의 대학·산업대학·교육대학 중 대학원이 설치된 대학\n\n**관련 법령:** 「교육공무원법」 제44조, 「행정 권한의 위임 및 위탁에 관한 규정」 제26조, 「교육공무원인사관리규정」 제24조, 「초·중등교육법」 제2조",
      "sources": [
        {
          "page": 143,
          "title": "경기도교육청 교육공무원 연수휴직을 위한 연수기관 지정에 관한 규칙",
          "text": "경기도 교육규칙 제583호 2009.08.07.\n**제1조(목적)** 이 규칙은 「교육공무원법」제44조 제1항 제8호, 「행정 권한의 위임 및 위탁에 관한 규정」제26조 제1항 제32호 및 「교육공무원인사관리규정」제24조에 따라 경기도교육청 소속 교육공무원의 연수휴직을 위한 연수기관 지정과 연수휴직의 범위 등을 규정함을 목적으로 한다.\n**제2조(정의)** 이 규칙에서 사용하는 용어의 뜻은 다음과 같다.\n1. \"연수휴직\"이란 「교육공무원법」제44조 제1항 제8호에 따라 임용권자로부터 허가를 받아 휴직함을 말한다.\n2. \"연수기관\"이란 연수휴직을 하고 연수를 받을 수 있는 국내의 연구기관이나 교육기관 등을 말한다.\n**제3조(적용 범위)** 이 규칙은 「초·중등교육법」제2조에 규정된 공립의 각급 학교에서 근무하는 교원과 교육기관·교육행정기관 및 교육연구기관에서 근무하는 교육전문직공무원에게 적용한다."
        }
      ],
      "category": "휴직 및 복직",
      "subcategory": "휴직 및 복직",
      "keywords": [
        "제2조(정의)",
        "휴직",
        "행정 권한의 위임 및 위탁에 관한 규정",
        "제1조(목적)",
        "교육공무원법",
        "교육공무원인사관리규정"
      ]
    }
  },
  {
    "id": "q_3_0621",
    "page": [
      143
    ],
    "entry": {
      "id": "q_3_0621",
      "question": "경기도교육청 교육공무원 연수휴직을 위한 연수기관 지정에 관한 규칙에서 자주 혼동되는 부분은 무엇인가요?",
      "answer": "경기도교육청 교육공무원 연수휴직을 위한 연수기관 지정에 관한 규칙 관련 내용을 안내해 드리겠습니다.\n\n**주요 내용:**\n- 경기도 교육규칙 제583호 2009.08.07.\n- **제1조(목적):** 이 규칙은 「교육공무원법」제44조 제1항 제8호, 「행정 권한의 위임 및 위탁에 관한 규정」제26조 제1항 제32호 및 「교육공무원인사관리규정」제24조에 따라 경기도교육청 소속 교육공무원의 연수휴직을 위한 연수기관 지정과 연수휴직의 범위 등을 규정함을 목적으로 한다.\n- **제2조(정의):** 이 규칙에서 사용하는 용어의 뜻은 다음과 같다.\n\n**세부 사항:**\n- 1. \"연수휴직\"이란 「교육공무원법」제44조 제1항 제8호에 따라 임용권자로부터 허가를 받아 휴직함을 말한다.\n- 2. \"연수기관\"이란 연수휴직을 하고 연수를 받을 수 있는 국내의 연구기관이나 교육기관 등을 말한다.\n- **제3조(적용 범위):** 이 규칙은 「초·중등교육법」제2조에 규정된 공립의 각급 학교에서 근무하는 교원과 교육기관·교육행정기관 및 교육연구기관에서 근무하는 교육전문직공무원에게 적용한다.\n- **제4조(연수기관의 지정):** 「행정 권한의 위임 및 위탁에 관한 규정」제26조 제1항 제32호에 따라 교육공무원이 연수휴직을 하고 연수를 받을 수 있는 연수기관은 다음 각 호와 같다. 다만, 원격대학원은 제외한다.\n- 1. 「고등교육법」제2조의 대학·산업대학·교육대학 중 대학원이 설치된 대학\n\n**관련 법령:** 「교육공무원법」 제44조, 「행정 권한의 위임 및 위탁에 관한 규정」 제26조, 「교육공무원인사관리규정」 제24조, 「초·중등교육법」 제2조",
      "sources": [
        {
          "page": 143,
          "title": "경기도교육청 교육공무원 연수휴직을 위한 연수기관 지정에 관한 규칙",
          "text": "경기도 교육규칙 제583호 2009.08.07.\n**제1조(목적)** 이 규칙은 「교육공무원법」제44조 제1항 제8호, 「행정 권한의 위임 및 위탁에 관한 규정」제26조 제1항 제32호 및 「교육공무원인사관리규정」제24조에 따라 경기도교육청 소속 교육공무원의 연수휴직을 위한 연수기관 지정과 연수휴직의 범위 등을 규정함을 목적으로 한다.\n**제2조(정의)** 이 규칙에서 사용하는 용어의 뜻은 다음과 같다.\n1. \"연수휴직\"이란 「교육공무원법」제44조 제1항 제8호에 따라 임용권자로부터 허가를 받아 휴직함을 말한다.\n2. \"연수기관\"이란 연수휴직을 하고 연수를 받을 수 있는 국내의 연구기관이나 교육기관 등을 말한다.\n**제3조(적용 범위)** 이 규칙은 「초·중등교육법」제2조에 규정된 공립의 각급 학교에서 근무하는 교원과 교육기관·교육행정기관 및 교육연구기관에서 근무하는 교육전문직공무원에게 적용한다."
        }
      ],
      "category": "휴직 및 복직",
      "subcategory": "휴직 및 복직",
      "keywords": [
        "제2조(정의)",
        "휴직",
        "행정 권한의 위임 및 위탁에 관한 규정",
        "제1조(목적)",
        "교육공무원법",
        "교육공무원인사관리규정"
      ]
    }
  },
  {
    "id": "q_3_0622",
    "page": [
      143
    ],
    "entry": {
      "id": "q_3_0622",
      "question": "봉급: 지급안함. 단, 휴직한 날이 속하는 달의 봉급은에 대해 자세히 설명해주세요.",
      "answer": "경기도교육청 교육공무원 연수휴직을 위한 연수기관 지정에 관한 규칙의 세부 내용을 안내드립니다.\n\n봉급: 지급안함. 단, 휴직한 날이 속하는 달의 봉급은 일할계산하여 지급   - (2) 수당: 지급안함. 단, 휴직한 날이 속하는 달의 수당은 일할계산하여 지급  ---  ## 경기도교육청 교육공무원 연수휴직을 위한 연수기관 지정에 관한 규칙  경기도 교육규칙 제583호 2009.08.07.",
      "sources": [
        {
          "page": 143,
          "title": "경기도교육청 교육공무원 연수휴직을 위한 연수기관 지정에 관한 규칙",
          "text": "봉급: 지급안함. 단, 휴직한 날이 속하는 달의 봉급은 일할계산하여 지급   - (2) 수당: 지급안함. 단, 휴직한 날이 속하는 달의 수당은 일할계산하여 지급  ---  ## 경기도교육청 교육공무원 연수휴직을 위한 연수기관 지정에 관한 규칙  경기도 교육규칙 제583호 2009.08.07."
        }
      ],
      "category": "휴직 및 복직",
      "subcategory": "휴직 및 복직",
      "keywords": [
        "휴직",
        "경기도교육청 교육공무원 연수휴직을 위한 연수기관 지정에 관한 규칙"
      ]
    }
  },
  {
    "id": "q_3_0623",
    "page": [
      143
    ],
    "entry": {
      "id": "q_3_0623",
      "question": "휴직 및 복직에서 경기도교육청 교육공무원 연수휴직을 위한 연수기관 지정에 관한 규칙이 중요한 이유는 무엇인가요?",
      "answer": "경기도교육청 교육공무원 연수휴직을 위한 연수기관 지정에 관한 규칙에 대한 주요 내용을 안내드립니다.\n\n- **나)** 휴직자가 휴직기간의 만료로 30일 이내에 복귀신고를 한 때에는 당연 복직됨. 이 경우 복직발령일 전일까지는 「교육공무원법」 제45조의 휴직기간으로 봄\n**7) 기타** \n- **가)** 휴직기간의 재직경력 인정여부\n- (1) 경력평정: 50% 산입\n- (2) 호봉승급: 승급제한. 단, 상위자격의 학위취득을 하였거나 교육경력의 산입으로 호봉을 재획정할 필요가 있을 때는 호봉을 재획정함\n- **나)** 결원보충: 6월 이상 휴직 시 별도정원에 의한 결원보충\n- **다)** 보수\n- (1) 봉급: 지급안함. 단, 휴직한 날이 속하는 달의 봉급은 일할계산하여 지급\n- (2) 수당: 지급안함. 단, 휴직한 날이 속하는 달의 수당은 일할계산하여 지급\n\n**경기도교육청 교육공무원 연수휴직을 위한 연수기관 지정에 관한 규칙**\n경기도 교육규칙 제583호 2009.08.07.\n**제1조(목적)**  이 규칙은 「교육공무원법」제44조 제1항 제8호, 「행정 권한의 위임 및 위탁에 관한 규정」제26조 제1항 제32호 및 「교육공무원인사관리규정」제24조에 따라 경기도교육청 소속 교육공무원의 연수휴직을 위한 연수기관 지정과 연수휴직의 범위 등을 규정함을 목적으로 한다.\n\n**관련 근거:** 「교육공무원법」 제45조, 「교육공무원법」 제44조, 「행정 권한의 위임 및 위탁에 관한 규정」 제26조, 「교육공무원인사관리규정」 제24조",
      "sources": [
        {
          "page": 143,
          "title": "경기도교육청 교육공무원 연수휴직을 위한 연수기관 지정에 관한 규칙",
          "text": "- **나)** 휴직자가 휴직기간의 만료로 30일 이내에 복귀신고를 한 때에는 당연 복직됨. 이 경우 복직발령일 전일까지는 「교육공무원법」 제45조의 휴직기간으로 봄\n\n**7) 기타**\n\n- **가)** 휴직기간의 재직경력 인정여부\n  - (1) 경력평정: 50% 산입\n  - (2) 호봉승급: 승급제한. 단, 상위자격의 학위취득을 하였거나 교육경력의 산입으로 호봉을 재획정할 필요가 있을 때는 호봉을 재획정함\n- **나)** 결원보충: 6월 이상 휴직 시 별도정원에 의한 결원보충\n- **다)** 보수\n  - (1) 봉급: 지급안함. 단, 휴직한 날이 속하는 달의 봉급은 일할계산하여 지급\n  - (2) 수당: 지급안함. 단, 휴직한 날이 속하는 달의 수당은 일할계산하여 지급\n\n---\n\n## 경기도교육청 교육공무원 연수휴직을 위한 연수기관 지정에 관한 규칙\n\n경기도 교육규칙 제583호 2009.08.07.\n\n**제1조(목적)** 이 규칙은 「교육공무원법」제44조 제1항 제8"
        }
      ],
      "category": "휴직 및 복직",
      "subcategory": "경기도교육청 교육공무원 연수휴직을 위",
      "keywords": [
        "승급",
        "교원",
        "휴직",
        "수당",
        "연수휴직",
        "경력평정",
        "봉급"
      ]
    }
  }
]