[
  {
    "id": "q_5_1551",
    "question": "기간제교원 육아휴직/복직 NEIS 발령처리에서 실무적으로 주의할 점은 무엇인가요?",
    "answer": "기간제교원 육아휴직/복직 NEIS 발령처리를 안내드립니다.\n\n**핵심 내용:**\n- 단위학교 교원인사권한자가 임용기안문을 작성ㆍ시행\n\n- NEIS 메뉴 위치 : 교원인사 - 임용발령 – 임용기안문작성(휴복직) – 휴직 / 복직\n**① (임용기안문 개요 생성):** 행추가 → 제목/기안일자/공개여부 등 임용기안문 입력 → 저장\n**② (임용기안문 세부내용 작성):** 추가된 임용기안 제목 클릭 → 세부내용 작성 → 저장 → 완료\n※ 내용 : 임용구분 \"남녀고용평등법:기간제교원육아휴직\", 휴직기간, 별도정원여부(비포함) 등을 입력\n**③ (결재 후 시행):** 임용기안문 승인요청(상신) → (결재) → 시행\n※ 시행 후 즉시 근무사항의 재직상태가 변경되므로 임용일경에 시행을 원칙으로 함(급여 연계됨)\n※ 과거 육아휴직 이력은 고용보험(http://www.ei.go.kr)에서 확인함(상기 Q&A 참고)\n※ 계약제교원 자료전송 기능으로 인사기록카드를 이관 받았을 때 [rydfyr]의 육아휴직 사항은 [임용전 경력]에 옮겨 기록하지 않음",
    "sources": [
      {
        "page": 428,
        "title": "기간제교원 육아휴직/복직 NEIS 발령처리",
        "text": "- 단위학교 교원인사권한자가 임용기안문을 작성ㆍ시행\n- NEIS 메뉴 위치 : 교원인사 - 임용발령 – 임용기안문작성(휴복직) – 휴직 / 복직\n**① (임용기안문 개요 생성)** 행추가 → 제목/기안일자/공개여부 등 임용기안문 입력 → 저장\n**② (임용기안문 세부내용 작성)** 추가된 임용기안 제목 클릭 → 세부내용 작성 → 저장 → 완료\n※ 내용 : 임용구분 \"남녀고용평등법:기간제교원육아휴직\", 휴직기간, 별도정원여부(비포함) 등을 입력\n**③ (결재 후 시행)** 임용기안문 승인요청(상신) → (결재) → 시행\n※ 시행 후 즉시 근무사항의 재직상태가 변경되므로 임용일경에 시행을 원칙으로 함(급여 연계됨)\n※ 과거 육아휴직 이력은 고용보험(http://www.ei.go.kr)에서 확인함(상기 Q&A 참고)\n※ 계약제교원 자료전송 기능으로 인사기록카드를 이관 받았을 때 [rydfyr]의 육아휴직 사항은 [임용전 경력]에 옮겨 기록하지 않음"
      }
    ],
    "category": "계약제교원",
    "subcategory": "기간제교사 육아휴직 시행 안내",
    "keywords": [
      "임용",
      "③ (결재 후 시행)",
      "휴직",
      "교원",
      "육아휴직",
      "복직"
    ]
  },
  {
    "id": "q_5_1553",
    "question": "학교장이 기간제교원 육아휴직/복직 NEIS 발령처리 관련하여 권한이 있나요?",
    "answer": "기간제교원 육아휴직/복직 NEIS 발령처리의 주요 내용을 정리해 드리겠습니다.\n\n**관련 분야:** 기간제교사 육아휴직 시행 안내\n\n**주요 내용:**\n- 단위학교 교원인사권한자가 임용기안문을 작성ㆍ시행\n- NEIS 메뉴 위치 : 교원인사 - 임용발령 – 임용기안문작성(휴복직) – 휴직 / 복직\n- **① (임용기안문 개요 생성):** 행추가 → 제목/기안일자/공개여부 등 임용기안문 입력 → 저장\n\n**세부 사항:**\n- **② (임용기안문 세부내용 작성):** 추가된 임용기안 제목 클릭 → 세부내용 작성 → 저장 → 완료\n※ 내용 : 임용구분 \"남녀고용평등법:기간제교원육아휴직\", 휴직기간, 별도정원여부(비포함) 등을 입력\n- **③ (결재 후 시행):** 임용기안문 승인요청(상신) → (결재) → 시행\n※ 시행 후 즉시 근무사항의 재직상태가 변경되므로 임용일경에 시행을 원칙으로 함(급여 연계됨)\n※ 과거 육아휴직 이력은 고용보험(http://www.ei.go.kr)에서 확인함(상기 Q&A 참고)",
    "sources": [
      {
        "page": 428,
        "title": "기간제교원 육아휴직/복직 NEIS 발령처리",
        "text": "- 단위학교 교원인사권한자가 임용기안문을 작성ㆍ시행\n- NEIS 메뉴 위치 : 교원인사 - 임용발령 – 임용기안문작성(휴복직) – 휴직 / 복직\n**① (임용기안문 개요 생성)** 행추가 → 제목/기안일자/공개여부 등 임용기안문 입력 → 저장\n**② (임용기안문 세부내용 작성)** 추가된 임용기안 제목 클릭 → 세부내용 작성 → 저장 → 완료\n※ 내용 : 임용구분 \"남녀고용평등법:기간제교원육아휴직\", 휴직기간, 별도정원여부(비포함) 등을 입력\n**③ (결재 후 시행)** 임용기안문 승인요청(상신) → (결재) → 시행\n※ 시행 후 즉시 근무사항의 재직상태가 변경되므로 임용일경에 시행을 원칙으로 함(급여 연계됨)\n※ 과거 육아휴직 이력은 고용보험(http://www.ei.go.kr)에서 확인함(상기 Q&A 참고)\n※ 계약제교원 자료전송 기능으로 인사기록카드를 이관 받았을 때 [rydfyr]의 육아휴직 사항은 [임용전 경력]에 옮겨 기록하지 않음"
      }
    ],
    "category": "계약제교원",
    "subcategory": "계약제교원",
    "keywords": [
      "임용",
      "복직",
      "휴직",
      "① (임용기안문 개요 생성)",
      "교원",
      "③ (결재 후 시행)"
    ]
  },
  {
    "id": "q_5_1554",
    "question": "기간제교원 육아휴직/복직 NEIS 발령처리의 행정 처리 담당자는 누구인가요?",
    "answer": "기간제교원 육아휴직/복직 NEIS 발령처리 관련 내용을 안내해 드리겠습니다.\n\n**관련 분야:** 기간제교사 육아휴직 시행 안내\n\n**주요 내용:**\n- 단위학교 교원인사권한자가 임용기안문을 작성ㆍ시행\n- NEIS 메뉴 위치 : 교원인사 - 임용발령 – 임용기안문작성(휴복직) – 휴직 / 복직\n- **① (임용기안문 개요 생성):** 행추가 → 제목/기안일자/공개여부 등 임용기안문 입력 → 저장\n\n**세부 사항:**\n- **② (임용기안문 세부내용 작성):** 추가된 임용기안 제목 클릭 → 세부내용 작성 → 저장 → 완료\n※ 내용 : 임용구분 \"남녀고용평등법:기간제교원육아휴직\", 휴직기간, 별도정원여부(비포함) 등을 입력\n- **③ (결재 후 시행):** 임용기안문 승인요청(상신) → (결재) → 시행\n※ 시행 후 즉시 근무사항의 재직상태가 변경되므로 임용일경에 시행을 원칙으로 함(급여 연계됨)\n※ 과거 육아휴직 이력은 고용보험(http://www.ei.go.kr)에서 확인함(상기 Q&A 참고)",
    "sources": [
      {
        "page": 428,
        "title": "기간제교원 육아휴직/복직 NEIS 발령처리",
        "text": "- 단위학교 교원인사권한자가 임용기안문을 작성ㆍ시행\n- NEIS 메뉴 위치 : 교원인사 - 임용발령 – 임용기안문작성(휴복직) – 휴직 / 복직\n**① (임용기안문 개요 생성)** 행추가 → 제목/기안일자/공개여부 등 임용기안문 입력 → 저장\n**② (임용기안문 세부내용 작성)** 추가된 임용기안 제목 클릭 → 세부내용 작성 → 저장 → 완료\n※ 내용 : 임용구분 \"남녀고용평등법:기간제교원육아휴직\", 휴직기간, 별도정원여부(비포함) 등을 입력\n**③ (결재 후 시행)** 임용기안문 승인요청(상신) → (결재) → 시행\n※ 시행 후 즉시 근무사항의 재직상태가 변경되므로 임용일경에 시행을 원칙으로 함(급여 연계됨)\n※ 과거 육아휴직 이력은 고용보험(http://www.ei.go.kr)에서 확인함(상기 Q&A 참고)\n※ 계약제교원 자료전송 기능으로 인사기록카드를 이관 받았을 때 [rydfyr]의 육아휴직 사항은 [임용전 경력]에 옮겨 기록하지 않음"
      }
    ],
    "category": "계약제교원",
    "subcategory": "계약제교원",
    "keywords": [
      "임용",
      "복직",
      "휴직",
      "① (임용기안문 개요 생성)",
      "교원",
      "③ (결재 후 시행)"
    ]
  },
  {
    "id": "q_5_1556",
    "question": "기간제교사 육아휴직 시행 안내에 대한 전반적인 내용을 요약해주세요.",
    "answer": "기간제교사 육아휴직 시행 안내에 대한 주요 내용을 안내드립니다.\n\n\n**기간제교사 육아휴직 시행 안내**\n\n**기간제교원 육아휴직/복직 NEIS 발령처리**\n- 단위학교 교원인사권한자가 임용기안문을 작성ㆍ시행\n- NEIS 메뉴 위치 : 교원인사 - 임용발령 – 임용기안문작성(휴복직) – 휴직 / 복직\n**① (임용기안문 개요 생성)**  행추가 → 제목/기안일자/공개여부 등 임용기안문 입력 → 저장\n**② (임용기안문 세부내용 작성)**  추가된 임용기안 제목 클릭 → 세부내용 작성 → 저장 → 완료\n※ 내용 : 임용구분 \"남녀고용평등법:기간제교원육아휴직\", 휴직기간, 별도정원여부(비포함) 등을 입력\n**③ (결재 후 시행)**  임용기안문 승인요청(상신) → (결재) → 시행\n※ 시행 후 즉시 근무사항의 재직상태가 변경되므로 임용일경에 시행을 원칙으로 함(급여 연계됨)\n※ 과거 육아휴직 이력은 고용보험(http://www.ei.go.kr)에서 확인함(상기 Q&A 참고)\n※ 계약제교원 자료전송 기능으로 인사기록카드를 이관 받았을 때 [rydfyr]의 육아휴직 사항은 [임용전 경력]에 옮겨 기록하지 않음",
    "sources": [
      {
        "page": 428,
        "title": "기간제교사 육아휴직 시행 안내",
        "text": "## 7. 기간제교사 육아휴직 시행 안내 (계속)\n\n### 기간제교원 육아휴직/복직 NEIS 발령처리\n\n- 단위학교 교원인사권한자가 임용기안문을 작성ㆍ시행\n- NEIS 메뉴 위치 : 교원인사 - 임용발령 – 임용기안문작성(휴복직) – 휴직 / 복직\n\n**① (임용기안문 개요 생성)** 행추가 → 제목/기안일자/공개여부 등 임용기안문 입력 → 저장\n\n**② (임용기안문 세부내용 작성)** 추가된 임용기안 제목 클릭 → 세부내용 작성 → 저장 → 완료\n\n※ 내용 : 임용구분 \"남녀고용평등법:기간제교원육아휴직\", 휴직기간, 별도정원여부(비포함) 등을 입력\n\n**③ (결재 후 시행)** 임용기안문 승인요청(상신) → (결재) → 시행\n\n※ 시행 후 즉시 근무사항의 재직상태가 변경되므로 임용일경에 시행을 원칙으로 함(급여 연계됨)\n\n---\n\n※ 과거 육아휴직 이력은 고용보험(http://www.ei.go.kr)에서 확인함(상기 Q&A 참고)\n\n※ 계약제교원 자료전송 기능으로 인"
      }
    ],
    "category": "계약제교원",
    "subcategory": "기간제교사 육아휴직 시행 안내",
    "keywords": [
      "기간제교사 육아휴직 시행 안내",
      "교원",
      "휴직",
      "기간제교원",
      "육아휴직",
      "복직",
      "교사"
    ]
  },
  {
    "id": "q_5_1557",
    "question": "기간제교사 육아휴직 시행 안내 과정에서 기간제교원 육아휴직/복직 NEIS 발령처리가 어떻게 적용되나요?",
    "answer": "기간제교사 육아휴직 시행 안내과 기간제교원 육아휴직/복직 NEIS 발령처리에 대한 주요 내용을 안내드립니다.\n\n\n**기간제교사 육아휴직 시행 안내**\n\n**기간제교원 육아휴직/복직 NEIS 발령처리**\n- 단위학교 교원인사권한자가 임용기안문을 작성ㆍ시행\n- NEIS 메뉴 위치 : 교원인사 - 임용발령 – 임용기안문작성(휴복직) – 휴직 / 복직\n**① (임용기안문 개요 생성)**  행추가 → 제목/기안일자/공개여부 등 임용기안문 입력 → 저장\n**② (임용기안문 세부내용 작성)**  추가된 임용기안 제목 클릭 → 세부내용 작성 → 저장 → 완료\n※ 내용 : 임용구분 \"남녀고용평등법:기간제교원육아휴직\", 휴직기간, 별도정원여부(비포함) 등을 입력\n**③ (결재 후 시행)**  임용기안문 승인요청(상신) → (결재) → 시행\n※ 시행 후 즉시 근무사항의 재직상태가 변경되므로 임용일경에 시행을 원칙으로 함(급여 연계됨)\n※ 과거 육아휴직 이력은 고용보험(http://www.ei.go.kr)에서 확인함(상기 Q&A 참고)\n※ 계약제교원 자료전송 기능으로 인사기록카드를 이관 받았을 때 [rydfyr]의 육아휴직 사항은 [임용전 경력]에 옮겨 기록하지 않음",
    "sources": [
      {
        "page": 428,
        "title": "기간제교사 육아휴직 시행 안내/기간제교원 육아휴직/복직 NEIS 발령처리",
        "text": "## 7. 기간제교사 육아휴직 시행 안내 (계속)\n\n### 기간제교원 육아휴직/복직 NEIS 발령처리\n\n- 단위학교 교원인사권한자가 임용기안문을 작성ㆍ시행\n- NEIS 메뉴 위치 : 교원인사 - 임용발령 – 임용기안문작성(휴복직) – 휴직 / 복직\n\n**① (임용기안문 개요 생성)** 행추가 → 제목/기안일자/공개여부 등 임용기안문 입력 → 저장\n\n**② (임용기안문 세부내용 작성)** 추가된 임용기안 제목 클릭 → 세부내용 작성 → 저장 → 완료\n\n※ 내용 : 임용구분 \"남녀고용평등법:기간제교원육아휴직\", 휴직기간, 별도정원여부(비포함) 등을 입력\n\n**③ (결재 후 시행)** 임용기안문 승인요청(상신) → (결재) → 시행\n\n※ 시행 후 즉시 근무사항의 재직상태가 변경되므로 임용일경에 시행을 원칙으로 함(급여 연계됨)\n\n---\n\n※ 과거 육아휴직 이력은 고용보험(http://www.ei.go.kr)에서 확인함(상기 Q&A 참고)\n\n※ 계약제교원 자료전송 기능으로 인"
      }
    ],
    "category": "계약제교원",
    "subcategory": "기간제교사 육아휴직 시행 안내",
    "keywords": [
      "기간제교사 육아휴직 시행 안내",
      "교원",
      "휴직",
      "기간제교원",
      "기간제교원 육아휴직/복직 NEIS 발령처리",
      "육아휴직",
      "복직"
    ]
  },
  {
    "id": "q_5_1565",
    "question": "출산 예정일 이전에 자녀를 출산한 경우 주의해야 할 점이 있나요?",
    "answer": "Q1. 육아휴직 신청은 반드시 30일전에 해야 하는지?에 관해 안내드립니다.\n\n**분류:** 기간제교사 육아휴직 시행 안내 > 「남녀고용평등법」상 기간제교원의 육아휴직 관련 Q&A\n\n**핵심 내용:**\n☞ 휴직개시예정일의 **30일전까지 신청서를 제출**하여야 하며, 다음의 경우 휴직개시예정일의 7일전까지 신청 가능\n\n※ ① 출산 예정일 이전에 자녀를 출산한 경우\n※ ② 배우자의 사망, 부상, 질병 또는 신체적ㆍ정신적 장애나 배우자와의 이혼 등으로 해당 영유아를 양육하기 곤란한 경우\n※ 「남녀고용평등법 시행령」 제11조(육아휴직의 신청 등) 제1항 및 제2항\n\n**관련 근거:** 「남녀고용평등법 시행령」 제11조",
    "sources": [
      {
        "page": 429,
        "title": "Q1. 육아휴직 신청은 반드시 30일전에 해야 하는지?",
        "text": "☞ 휴직개시예정일의 **30일전까지 신청서를 제출**하여야 하며, 다음의 경우 휴직개시예정일의 7일전까지 신청 가능\n① 출산 예정일 이전에 자녀를 출산한 경우\n② 배우자의 사망, 부상, 질병 또는 신체적ㆍ정신적 장애나 배우자와의 이혼 등으로 해당 영유아를 양육하기 곤란한 경우\n※ 「남녀고용평등법 시행령」 제11조(육아휴직의 신청 등) 제1항 및 제2항"
      }
    ],
    "category": "계약제교원",
    "subcategory": "기간제교사 육아휴직 시행 안내",
    "keywords": [
      "30일전까지 신청서를 제출",
      "남녀고용평등법 시행령",
      "육아휴직",
      "휴직"
    ]
  },
  {
    "id": "q_5_1594",
    "question": "학교장이 Q2. 타 학교에서 1년의 육아휴직을 사용한 후, 새로운 학교에서 동일한 자녀의 양육을 사유로 신청할 경우 허용해야 하는지? 관련하여 권한이 있나요?",
    "answer": "질문하신 Q2. 타 학교에서 1년의 육아휴직을 사용한 후, 새로운 학교에서 동일한 자녀의 양육을 사유로 신청할 경우 허용해야 하는지?에 대해 답변드립니다.\n\n**관련 분야:** 기간제교사 육아휴직 시행 안내 > 「남녀고용평등법」상 기간제교원의 육아휴직 관련 Q&A > Q1. 육아휴직 신청은 반드시 30일전에 해야 하는지?\n\n**주요 내용:**\n- ☞ 동일한 자녀에 대하여 **1년의 육아휴직을 이미 사용하였다면**, 새로운 학교에서 육아휴직 **사용불가**(모성보호와 일ㆍ가정 양립 지원 업무편람('19.10))\n※ 이전 학교에서 기간제교원으로 6개월 근무 후 6개월 육아휴직을 한 경우, 현재 학교에서 6개월 이상 근무 시 6개월 육아휴직은 신청 가능\n※ 1년 근무 후 동일학교에서 1년 재계약 시에는 3.1.부터 육아휴직 가능\n\n**세부 사항:**\n- > ※ 이미 사용한 육아휴직의 조회가 필요한 경우,\n- > ⇒ 고용보험(http://www.ei.go.kr)을 통해 기업회원 로그인 후 지원금 지급내역 조회 - 모성보호 메뉴를 통해 **현 근무지에서 사용한 육아휴직 개별 조회** 가능\n- > ⇒ 전 근무지에서 사용한 육아휴직 조회의 경우 **기간제교원 본인 동의 후** 고용보험(http://www.ei.go.kr)을 통해 **육아휴직 사용 혹은 급여내역으로 확인** 가능",
    "sources": [
      {
        "page": 429,
        "title": "Q2. 타 학교에서 1년의 육아휴직을 사용한 후, 새로운 학교에서 동일한 자녀의 양육을 사유로 신청할 경우 허용해야 하는지?",
        "text": "☞ 동일한 자녀에 대하여 **1년의 육아휴직을 이미 사용하였다면**, 새로운 학교에서 육아휴직 **사용불가**(모성보호와 일ㆍ가정 양립 지원 업무편람('19.10))\n※ 이전 학교에서 기간제교원으로 6개월 근무 후 6개월 육아휴직을 한 경우, 현재 학교에서 6개월 이상 근무 시 6개월 육아휴직은 신청 가능\n※ 1년 근무 후 동일학교에서 1년 재계약 시에는 3.1.부터 육아휴직 가능\n※ 이미 사용한 육아휴직의 조회가 필요한 경우,\n⇒ 고용보험(http://www.ei.go.kr)을 통해 기업회원 로그인 후 지원금 지급내역 조회 - 모성보호 메뉴를 통해 **현 근무지에서 사용한 육아휴직 개별 조회** 가능\n⇒ 전 근무지에서 사용한 육아휴직 조회의 경우 **기간제교원 본인 동의 후** 고용보험(http://www.ei.go.kr)을 통해 **육아휴직 사용 혹은 급여내역으로 확인** 가능"
      }
    ],
    "category": "계약제교원",
    "subcategory": "계약제교원",
    "keywords": [
      "사용불가",
      "교원",
      "휴직"
    ]
  },
  {
    "id": "q_5_1602",
    "question": "기간제교사 육아휴직 시행 안내의 ①번째 항목은 무엇인가요?",
    "answer": "기간제교사 육아휴직 시행 안내의 세부 내용을 안내드립니다.\n\n**관련 분류:** 기간제교사 육아휴직 시행 안내\n\n출산 예정일 이전에 자녀를 출산한 경우 > ② 배우자의 사망, 부상, 질병 또는 신체적ㆍ정신적 장애나 배우자와의 이혼 등으로 해당 영유아를 양육하기 곤란한 경우  ※ 「남녀고용평등법 시행령」 제11조(육아휴직의 신청 등) 제1항 및 제2항  ---\n\n**관련 근거:** 「남녀고용평등법 시행령」 제11조",
    "sources": [
      {
        "page": 429,
        "title": "기간제교사 육아휴직 시행 안내",
        "text": "출산 예정일 이전에 자녀를 출산한 경우 > ② 배우자의 사망, 부상, 질병 또는 신체적ㆍ정신적 장애나 배우자와의 이혼 등으로 해당 영유아를 양육하기 곤란한 경우  ※ 「남녀고용평등법 시행령」 제11조(육아휴직의 신청 등) 제1항 및 제2항  ---"
      }
    ],
    "category": "계약제교원",
    "subcategory": "기간제교사 육아휴직 시행 안내",
    "keywords": [
      "기간제교사 육아휴직 시행 안내",
      "휴직"
    ]
  },
  {
    "id": "q_5_1603",
    "question": "기간제교사 육아휴직 시행 안내에서 「남녀고용평등법」상 기간제교원의 육아휴직 관련 Q&A에 대한 규정은 무엇인가요?",
    "answer": "기간제교사 육아휴직 시행 안내과 「남녀고용평등법」상 기간제교원의 육아휴직 관련 Q&A에 대한 주요 내용을 안내드립니다.\n\n\n**기간제교사 육아휴직 시행 안내**\n\n**「남녀고용평등법」상 기간제교원의 육아휴직 관련 Q&A**\n**Q1. 육아휴직 신청은 반드시 30일전에 해야 하는지?** \n☞ 휴직개시예정일의 **30일전까지 신청서를 제출**하여야 하며, 다음의 경우 휴직개시예정일의 7일전까지 신청 가능\n※ ① 출산 예정일 이전에 자녀를 출산한 경우\n※ ② 배우자의 사망, 부상, 질병 또는 신체적ㆍ정신적 장애나 배우자와의 이혼 등으로 해당 영유아를 양육하기 곤란한 경우\n※ 「남녀고용평등법 시행령」 제11조(육아휴직의 신청 등) 제1항 및 제2항\n**Q2. 타 학교에서 1년의 육아휴직을 사용한 후, 새로운 학교에서 동일한 자녀의 양육을 사유로 신청할 경우 허용해야 하는지?** \n☞ 동일한 자녀에 대하여 **1년의 육아휴직을 이미 사용하였다면**, 새로운 학교에서 육아휴직 **사용불가**(모성보호와 일ㆍ가정 양립 지원 업무편람('19.10))\n※ 이전 학교에서 기간제교원으로 6개월 근무 후 6개월 육아휴직을 한 경우, 현재 학교에서 6개월 이상 근무 시 6개월 육아휴직은 신청 가능\n※ 1년 근무 후 동일학교에서 1년 재계약 시에는 3.1.부터 육아휴직 가능\n※ ※ 이미 사용한 육아휴직의 조회가 필요한 경우,\n\n**관련 근거:** 「남녀고용평등법」, 「남녀고용평등법 시행령」 제11조, 「남녀고용평등법 시행령」 제10조, 「남녀고용평등법」 제18조",
    "sources": [
      {
        "page": 429,
        "title": "기간제교사 육아휴직 시행 안내/「남녀고용평등법」상 기간제교원의 육아휴직 관련 Q&A",
        "text": "## 7. 기간제교사 육아휴직 시행 안내 (계속)\n\n### 「남녀고용평등법」상 기간제교원의 육아휴직 관련 Q&A\n\n---\n\n**Q1. 육아휴직 신청은 반드시 30일전에 해야 하는지?**\n\n☞ 휴직개시예정일의 **30일전까지 신청서를 제출**하여야 하며, 다음의 경우 휴직개시예정일의 7일전까지 신청 가능\n\n> ① 출산 예정일 이전에 자녀를 출산한 경우\n> ② 배우자의 사망, 부상, 질병 또는 신체적ㆍ정신적 장애나 배우자와의 이혼 등으로 해당 영유아를 양육하기 곤란한 경우\n\n※ 「남녀고용평등법 시행령」 제11조(육아휴직의 신청 등) 제1항 및 제2항\n\n---\n\n**Q2. 타 학교에서 1년의 육아휴직을 사용한 후, 새로운 학교에서 동일한 자녀의 양육을 사유로 신청할 경우 허용해야 하는지?**\n\n☞ 동일한 자녀에 대하여 **1년의 육아휴직을 이미 사용하였다면**, 새로운 학교에서 육아휴직 **사용불가**(모성보호와 일ㆍ가정 양립 지원 업무편람('19.10))\n\n※ 이전 학교에"
      }
    ],
    "category": "계약제교원",
    "subcategory": "기간제교사 육아휴직 시행 안내",
    "keywords": [
      "기간제교사 육아휴직 시행 안내",
      "「남녀고용평등법」상 기간제교원의 육아휴직 관련 Q&A",
      "교원",
      "휴직",
      "기간제교원",
      "육아휴직",
      "교사"
    ]
  },
  {
    "id": "q_5_1605",
    "question": "기간제교사가 육아휴직 중인데 정규교원이 조기복직하면 해고할 수 있나요?",
    "answer": "기간제교사 육아휴직 중 정규교원 조기복직 시:\n\n**결론**: **해고할 수 없음**\n\n**근거** (남녀고용평등법 제19조제3항):\n- 육아휴직을 이유로 **해고나 그 밖의 불리한 처우를 하여서는 아니 됨**\n- 육아휴직 기간에는 **실직의 위험에서 벗어나 안정적으로 영아 보육에 전념**할 수 있도록 보장\n\n**위반 시 조치**:\n- 육아휴직 기간에 해고가 발생한 경우\n- 반드시 **고용노동청 근로개선지도과**로 통보\n- **법 위반 사실을 조사**할 수 있도록 함 (감사원 지적사항)\n\n**육아휴직 관련 퇴직금 산정**:\n- 육아휴직 기간은 퇴직금 산정의 기초가 되는 **근속기간에 포함**\n- 단, **평균임금 산정 시에는 제외**\n  - 평균임금 기준 기간과 임금 총액에서 각각 제외\n  (근로기준법 시행령 제2조제1항제5호)\n\n**출처**: 모성보호와 일·가정 양립 지원 업무편람('19.10)",
    "sources": [
      {
        "page": 430,
        "title": "육아휴직 해고 불가",
        "text": "육아휴직 기간에는 해고할 수 없으며, 육아휴직 중 실직의 위험에서 벗어나 안정적으로 영아의 보육에 전념할 수 있도록 「남녀고용평등법」 제19조 제3항에 따라 육아휴직을 이유로 해고나 그 밖의 불리한 처우를 하여서는 아니 됨"
      },
      {
        "page": 430,
        "title": "위반 시 조치",
        "text": "육아휴직 기간에 해고가 발생한 경우 반드시 고용노동청 근로개선지도과로 통보하여 법 위반 사실을 조사(감사원 지적사항)할 수 있도록 함"
      }
    ],
    "category": "계약제교원",
    "subcategory": "육아휴직",
    "keywords": [
      "육아휴직",
      "해고금지",
      "조기복직",
      "남녀고용평등법",
      "근속기간"
    ]
  }
]